pyrsakeyutils/__init__.py
pyrsakeyutils/rsautil.py
pyrsakeyutils/rsautils_test.py
pyrsakeyutils-0.1.0.dist-info/LICENSE
pyrsakeyutils-0.1.0.dist-info/METADATA
pyrsakeyutils-0.1.0.dist-info/WHEEL
pyrsakeyutils-0.1.0.dist-info/RECORD
